greenWTE/__init__.py
greenWTE/base.py
greenWTE/green.py
greenWTE/io.py
greenWTE/iterative.py
greenWTE/nvtx_utils.py
greenWTE/post.py
greenWTE/precompute_green.py
greenWTE/solve_green.py
greenWTE/solve_iter.py
greenWTE/sources.py
greenWTE/tests/__init__.py
greenWTE/tests/defaults.py
greenWTE/tests/test_base_classes.py
greenWTE/tests/test_cli.py
greenWTE/tests/test_green.py
greenWTE/tests/test_io.py
greenWTE/tests/test_nvtx.py
greenWTE/tests/test_physics.py
greenWTE/tests/test_sources.py
greenwte-1.0.1.dist-info/METADATA
greenwte-1.0.1.dist-info/WHEEL
greenwte-1.0.1.dist-info/licenses/LICENSE
greenwte-1.0.1.dist-info/RECORD
