Metadata-Version: 2.4
Name: greenWTE
Version: 1.0.1
Summary: Solve the Wigner Transport Equation with a source term!
Project-URL: Homepage, https://github.com/kremeyer/greenWTE
Project-URL: Documentation, https://greenwte.readthedocs.io
Project-URL: Repository, https://github.com/kremeyer/greenWTE
Project-URL: Changelog, https://github.com/kremeyer/greenWTE/blob/main/CHANGELOG.md
Project-URL: Author, https://scholar.google.com/citations?user=gKsq_08AAAAJ
Author-email: Laurenz Kremeyer <laurenz.kremeyer@mail.mcgill.ca>
License-Expression: BSD-3-Clause
License-File: LICENSE
Classifier: Development Status :: 5 - Production/Stable
Classifier: Environment :: GPU
Classifier: Intended Audience :: Science/Research
Classifier: License :: OSI Approved :: BSD License
Classifier: Topic :: Scientific/Engineering :: Physics
Requires-Python: >=3.10
Requires-Dist: h5py
Requires-Dist: hdf5plugin
Requires-Dist: numpy>=2
Requires-Dist: scipy~=1.15
Provides-Extra: cuda12x
Requires-Dist: cupy-cuda12x>=12.0; extra == 'cuda12x'
Provides-Extra: cuda13x
Requires-Dist: cupy-cuda13x>=13.0; extra == 'cuda13x'
Provides-Extra: docs
Requires-Dist: matplotlib; extra == 'docs'
Requires-Dist: sphinx; extra == 'docs'
Requires-Dist: sphinx-argparse; extra == 'docs'
Requires-Dist: sphinx-rtd-theme; extra == 'docs'
Requires-Dist: typing-extensions; extra == 'docs'
